myPackage/__init__.py
myPackage/simple.py
qumath_lukas0008-0.0.1.dist-info/METADATA
qumath_lukas0008-0.0.1.dist-info/WHEEL
qumath_lukas0008-0.0.1.dist-info/top_level.txt
qumath_lukas0008-0.0.1.dist-info/RECORD
