Metadata-Version: 2.1
Name: qumath-lukas0008
Version: 0.0.1
Summary: Simple math package
Home-page: https://github.com/lukas0008/qmath
Author: lukas0008
Author-email: lukzaj333@gmail.com
License: MIT
Platform: UNKNOWN
Requires-Python: >=3.6
